pycfmodel/__init__.py
pycfmodel/action_expander.py
pycfmodel/cloudformation_actions.py
pycfmodel/constants.py
pycfmodel/resolver.py
pycfmodel/utils.py
pycfmodel/model/base.py
pycfmodel/model/cf_model.py
pycfmodel/model/generic.py
pycfmodel/model/parameter.py
pycfmodel/model/types.py
pycfmodel/model/utils.py
pycfmodel/model/resources/ec2_vpc_endpoint_policy.py
pycfmodel/model/resources/es_domain.py
pycfmodel/model/resources/generic_resource.py
pycfmodel/model/resources/iam_group.py
pycfmodel/model/resources/iam_managed_policy.py
pycfmodel/model/resources/iam_policy.py
pycfmodel/model/resources/iam_role.py
pycfmodel/model/resources/iam_user.py
pycfmodel/model/resources/kms_key.py
pycfmodel/model/resources/opensearch_domain.py
pycfmodel/model/resources/resource.py
pycfmodel/model/resources/s3_bucket.py
pycfmodel/model/resources/s3_bucket_policy.py
pycfmodel/model/resources/security_group.py
pycfmodel/model/resources/security_group_egress.py
pycfmodel/model/resources/security_group_ingress.py
pycfmodel/model/resources/sns_topic_policy.py
pycfmodel/model/resources/sqs_queue_policy.py
pycfmodel/model/resources/types.py
pycfmodel/model/resources/wafv2_ip_set.py
pycfmodel/model/resources/properties/policy.py
pycfmodel/model/resources/properties/policy_document.py
pycfmodel/model/resources/properties/property.py
pycfmodel/model/resources/properties/security_group_egress_prop.py
pycfmodel/model/resources/properties/security_group_ingress_prop.py
pycfmodel/model/resources/properties/statement.py
pycfmodel/model/resources/properties/statement_condition.py
pycfmodel/model/resources/properties/tag.py
pycfmodel/model/resources/properties/types.py
pycfmodel-1.2.0.dist-info/licenses/LICENSE.md
pycfmodel-1.2.0.dist-info/METADATA
pycfmodel-1.2.0.dist-info/WHEEL
pycfmodel-1.2.0.dist-info/top_level.txt
pycfmodel-1.2.0.dist-info/RECORD
