Metadata-Version: 2.4
Name: pycfmodel
Version: 1.2.0
Summary: A python model for Cloud Formation scripts
Author-email: Skyscanner Security <security@skyscanner.net>
Project-URL: Homepage, https://github.com/Skyscanner/pycfmodel
Project-URL: Repository, https://github.com/Skyscanner/pycfmodel
Project-URL: Bug Tracker, https://github.com/Skyscanner/pycfmodel/issues
Project-URL: Documentation, https://pycfmodel.readthedocs.io
Project-URL: Changelog, https://github.com/Skyscanner/pycfmodel/releases
Requires-Python: >=3.9.0
License-File: LICENSE.md
Requires-Dist: pydantic~=2.7
Provides-Extra: dev
Requires-Dist: black>=22.1.0; extra == "dev"
Requires-Dist: httpx>=0.14.2; extra == "dev"
Requires-Dist: isort>=5.4.2; extra == "dev"
Requires-Dist: pip-tools>=2.0.2; extra == "dev"
Requires-Dist: pytest>=6.0.1; extra == "dev"
Requires-Dist: pytest-cov>=2.10.1; extra == "dev"
Requires-Dist: pytest-repeat==0.9.3; extra == "dev"
Requires-Dist: ruff; extra == "dev"
Provides-Extra: docs
Requires-Dist: AutoMacDoc==0.3; extra == "docs"
Requires-Dist: livereload==2.7.1; extra == "docs"
Requires-Dist: mkdocs-material==9.6.11; extra == "docs"
Requires-Dist: mkdocs==1.6.1; extra == "docs"
Requires-Dist: mkdocstrings==0.28.3; extra == "docs"
Dynamic: license-file
